bigquery_etl_tools/__init__.py
bigquery_etl_tools/bigquery_utils.py
bigquery_etl_tools/client.py
bigquery_etl_tools/config.py
bigquery_etl_tools/etl_utils.py
bigquery_etl_tools/file_utils.py
bigquery_etl_tools/storage_utils.py
tests/__init__.py
tests/test_core.py
tests/test_etl.py
tests/test_file_utils.py
tests/test_storage_utils.py
bigquery_etl_tools-0.0.4.dist-info/LICENSE.txt
bigquery_etl_tools-0.0.4.dist-info/METADATA
bigquery_etl_tools-0.0.4.dist-info/WHEEL
bigquery_etl_tools-0.0.4.dist-info/top_level.txt
bigquery_etl_tools-0.0.4.dist-info/RECORD
