Metadata-Version: 2.1
Name: bigquery_etl_tools
Version: 0.0.4
Summary: BigQuery ETL Tools
Home-page: https://github.com/Mattanalytix/bigquery-etl-tools
Author: mattanalytix
Author-email: info@mattanalytix.com
License-File: LICENSE.txt
